columnizer/__init__.py
columnizer/columnizer.py
columnizer-0.0.1.dist-info/LICENSE
columnizer-0.0.1.dist-info/METADATA
columnizer-0.0.1.dist-info/WHEEL
columnizer-0.0.1.dist-info/top_level.txt
columnizer-0.0.1.dist-info/RECORD
