Metadata-Version: 2.1
Name: columnizer
Version: 0.0.1
Summary: Simple, yet extendable ASCII text columnizer.
Home-page: https://github.com/mrmessagewriter/columnizer
Author: mr.message.writer
Author-email: mr.message.writer@gmail.com
License: UNKNOWN
Project-URL: Bug Tracker, https://github.com/mrmessagewriter/columnizer/issues
Platform: UNKNOWN
Classifier: Programming Language :: Python :: 3
Classifier: License :: OSI Approved :: MIT License
Classifier: Operating System :: OS Independent
Requires-Python: >=3.6
License-File: LICENSE
